jsonstore.py
pyfastkvjson-3.1.16.dist-info/LICENCE.md
pyfastkvjson-3.1.16.dist-info/METADATA
pyfastkvjson-3.1.16.dist-info/WHEEL
pyfastkvjson-3.1.16.dist-info/top_level.txt
pyfastkvjson-3.1.16.dist-info/RECORD
