Metadata-Version: 2.1
Name: pyfastkvjson
Version: 3.1.16
Summary: Json key store with secured feature.
Home-page: https://github.com/ONode/pyfastkvjson/
Author: Oliver Bristow, Heskemo
Author-email: github+pypi@oliverbristow.co.uk
License: MIT
Keywords: json key value store and more secured
Classifier: Development Status :: 5 - Production/Stable
Classifier: Intended Audience :: Developers
Classifier: License :: OSI Approved :: MIT License
Classifier: Operating System :: OS Independent
Classifier: Programming Language :: Python :: 3
Classifier: Programming Language :: Python :: 3.3
Classifier: Programming Language :: Python :: 3.4
Classifier: Programming Language :: Python :: 3.5
Classifier: Programming Language :: Python :: 3.6
Classifier: Programming Language :: Python :: 3.7
Classifier: Programming Language :: Python :: 3.8
Classifier: Programming Language :: Python :: 3.9
Classifier: Programming Language :: Python :: Implementation :: CPython
Classifier: Programming Language :: Python :: Implementation :: PyPy
Classifier: Topic :: Database
Classifier: Topic :: Software Development
License-File: LICENCE.md
Requires-Dist: pyAesCrypt (>=6.0.0)
